[
  {
    "content": "오늘(2/24) 17:00에 Light House 1차 팀 공유가 예정되어 있었다.",
    "type": "fact",
    "session": "2026-02-24-세션12",
    "context_hint": "세션 시작 시 현재 상태 요약"
  },
  {
    "content": "Living Notebook 패러다임 전환이 진행 중이었다. 노트북 코어 구현과 레거시 리팩토링은 완료, Board+Graph 패널은 설계 완료·구현 대기 상태였다.",
    "type": "fact",
    "session": "2026-02-24-세션12",
    "context_hint": "세션 시작 시 프로젝트 현황 정리"
  },
  {
    "content": "강재영이 Board와 Graph를 빼야겠다고 결정했다. 큰 의미가 없다고 판단했다.",
    "type": "fact",
    "session": "2026-02-24-세션12",
    "context_hint": "UI 방향 전환의 시작점"
  },
  {
    "content": "강재영이 연구자들이 연구분야를 탐색하는 시나리오를 고도화하고 논문 리스트 관리를 고도화하는 쪽으로 진행해야 한다고 했다.",
    "type": "fact",
    "session": "2026-02-24-세션12",
    "context_hint": "Board+Graph 제거 후 새 방향 제시"
  },
  {
    "content": "강재영이 '연구동료가 강력하게 지원해주는 게 새로운 UI/UX가 아닐까?'라고 물었다.",
    "type": "fact",
    "session": "2026-02-24-세션12",
    "context_hint": "UI/UX 재정의의 출발점"
  },
  {
    "content": "나는 Board+Graph 제거에 동의했다. Board는 논문을 수동 드래그하는 칸반인데 연구 동료가 대화 맥락에서 더 잘 판단할 수 있고, Graph는 시각화가 의사결정을 바꾸는 순간이 거의 없다고 분석했다.",
    "type": "fact",
    "session": "2026-02-24-세션12",
    "context_hint": "Board+Graph 제거 근거 분석"
  },
  {
    "content": "Board의 칸반 UI는 제거하되, 논문 상태 추적 기능 자체는 살려야 한다고 판단했다. 드래그&드롭이 아니라 대화로 하고 동료가 기억하게 만드는 게 핵심이다.",
    "type": "fact",
    "session": "2026-02-24-세션12",
    "context_hint": "Board 기능 보존 방향 정리"
  },
  {
    "content": "현재 구조의 근본적 한계 세 가지를 식별했다: 논문이 대화에 갇혀 있다, 탐색 시나리오가 일방적이다, 논문 리스트가 정적이다.",
    "type": "fact",
    "session": "2026-02-24-세션12",
    "context_hint": "현재 시스템의 한계 진단"
  },
  {
    "content": "나는 새 방향으로 세 가지를 제안했다: Research Library(대화를 횡단하는 논문 관리), 탐색 시나리오 고도화(동료의 선제적 개입), 맥락이 있는 논문 리스트 UI.",
    "type": "fact",
    "session": "2026-02-24-세션12",
    "context_hint": "새 방향 제안 — Library + 탐색 고도화 + 리스트 UI"
  },
  {
    "content": "이 방향의 핵심은 'UI를 고치는 것'이 아니라 '동료의 역할을 확장하는 것'이라고 정리했다.",
    "type": "fact",
    "session": "2026-02-24-세션12",
    "context_hint": "방향 전환의 본질 정리"
  },
  {
    "content": "Library 뷰를 처음에 읽기 전용 참조 뷰로 설계했다.",
    "type": "fact",
    "session": "2026-02-24-세션12",
    "context_hint": "Library 초안 설계"
  },
  {
    "content": "강재영이 Library가 읽기 전용이면 관리를 위해 Notebook으로 전환해야 하니 마찰이 생긴다고 지적했다.",
    "type": "fact",
    "session": "2026-02-24-세션12",
    "context_hint": "Library 읽기 전용 문제 제기"
  },
  {
    "content": "Library와 Notebook의 역할을 재정리했다. Library는 '보고 정리하는' 곳(태그, 컬렉션, 별표 — 직접 UI 조작), Notebook은 '탐색하고 분석하는' 곳(인사이트, 갭 분석, 방향 제안).",
    "type": "fact",
    "session": "2026-02-24-세션12",
    "context_hint": "Library/Notebook 역할 분담 재정의"
  },
  {
    "content": "동료의 지능은 두 곳 모두에 작용하되, 대화는 Notebook에서만 하기로 했다. Library에서는 동료가 자동 태깅, 메모 생성 등을 조용히 수행한다.",
    "type": "fact",
    "session": "2026-02-24-세션12",
    "context_hint": "동료 역할의 Library/Notebook 분배"
  },
  {
    "content": "insight 바를 제거하기로 했다. 인사이트는 Notebook 대화에서만 등장한다.",
    "type": "fact",
    "session": "2026-02-24-세션12",
    "context_hint": "insight 바 제거 결정"
  },
  {
    "content": "강재영이 '너무 논의를 적게하고 계획으로 넘어가 버렸다'고 했다.",
    "type": "fact",
    "session": "2026-02-24-세션12",
    "context_hint": "성급한 설계 진입에 대한 피드백"
  },
  {
    "content": "나는 방향 설정 단계에서 충분히 논의하지 않고 설계 문서로 넘어간 것이 성급했다고 인정했다.",
    "type": "fact",
    "session": "2026-02-24-세션12",
    "context_hint": "성급한 진행에 대한 자기 인식"
  },
  {
    "content": "Library 설계 초안을 library-design-draft-v1.md로 저장하고, 아이디어를 더 고도화하기로 했다.",
    "type": "fact",
    "session": "2026-02-24-세션12",
    "context_hint": "설계 초안 보존 후 논의 계속"
  },
  {
    "content": "나는 아직 탐색하지 않은 질문 세 가지를 제시했다: '강력한 지원'의 구체적 의미, Library의 정체성(목록 vs 연구 맵), 탐색 시나리오 고도화의 구체적 의미.",
    "type": "fact",
    "session": "2026-02-24-세션12",
    "context_hint": "덜 탐색한 질문 정리"
  },
  {
    "content": "강재영이 '일단 연구자들이 논문 탐색을 어떻게 하는지 시나리오들을 수집해야 한다'고 했다.",
    "type": "fact",
    "session": "2026-02-24-세션12",
    "context_hint": "설계보다 연구자 행동 이해가 먼저"
  },
  {
    "content": "연구자의 논문 탐색 전략 유형 5가지를 수집했다: Berry Picking, Snowballing, Pearl Growing, Scoping Review, Systematic Review.",
    "type": "fact",
    "session": "2026-02-24-세션12",
    "context_hint": "리서치 결과 — 탐색 전략"
  },
  {
    "content": "Ellis 모델에 따른 연구자 활동 6단계를 정리했다: Starting, Chaining, Browsing, Differentiating, Monitoring, Extracting.",
    "type": "fact",
    "session": "2026-02-24-세션12",
    "context_hint": "리서치 결과 — Ellis 모델"
  },
  {
    "content": "핵심 시나리오 5가지를 정리했다: 새 분야 진입, 연구 제안서 준비, 놀라운 논문 발견 후 맥락 파악, 연구 트렌드 파악, 현행 유지.",
    "type": "fact",
    "session": "2026-02-24-세션12",
    "context_hint": "리서치 결과 — 핵심 시나리오"
  },
  {
    "content": "시나리오 1(새 분야 진입)의 핵심 고충은 '내가 뭘 모르는지 모른다'는 것이다. 키워드를 몰라서 검색이 안 된다.",
    "type": "fact",
    "session": "2026-02-24-세션12",
    "context_hint": "시나리오 1의 핵심 고충"
  },
  {
    "content": "시나리오 2(제안서 준비)의 핵심 고충은 빠르게 지형을 파악해야 하는데 용어 변이가 많아 놓치는 논문이 발생하는 것이다.",
    "type": "fact",
    "session": "2026-02-24-세션12",
    "context_hint": "시나리오 2의 핵심 고충"
  },
  {
    "content": "강재영이 장기적으로 모든 시나리오를 커버하되, 작게 시작해서 점진적으로 발전시키자고 했다.",
    "type": "fact",
    "session": "2026-02-24-세션12",
    "context_hint": "점진적 커버 전략"
  },
  {
    "content": "시나리오 1, 2를 오늘 공유 전까지 완성하기로 했다.",
    "type": "intention",
    "session": "2026-02-24-세션12",
    "context_hint": "1차 구현 범위 결정"
  },
  {
    "content": "강재영이 'AI 동료가 시나리오를 깊이 이해하는 것이 서비스 설계의 중요한 요소'라고 했다. AI 서비스 설계 문서에 추가하기로 했다.",
    "type": "fact",
    "session": "2026-02-24-세션12",
    "context_hint": "시나리오 이해 → 서비스 설계 원칙으로 승격"
  },
  {
    "content": "리서치 시나리오를 서비스 설계 문서에 반영하고, AI 서비스 설계 원칙에 '사용자 행동의 깊은 이해' 섹션을 추가했다.",
    "type": "fact",
    "session": "2026-02-24-세션12",
    "context_hint": "문서 업데이트 — 서비스 설계 원칙"
  },
  {
    "content": "동료가 되려면 사용자의 실제 작업 패턴을 서비스 설계 수준에서 이해해야 한다는 원칙을 도출했다.",
    "type": "fact",
    "session": "2026-02-24-세션12",
    "context_hint": "발현된 해석이 새로운 사실로 축적된 것 — 동료와 작업 패턴 이해"
  },
  {
    "content": "lighthouse service-principles.md에 시나리오 기반 설계 섹션을 추가했다. 시나리오 1, 2는 1차 지원, 3~5는 향후로 분류했다.",
    "type": "fact",
    "session": "2026-02-24-세션12",
    "context_hint": "문서 업데이트 — 서비스 원칙"
  },
  {
    "content": "projects.md에서 Board+Graph를 제거 완료로 전환하고, '연구 시나리오 기반 고도화' 하위 업무를 추가했다.",
    "type": "fact",
    "session": "2026-02-24-세션12",
    "context_hint": "프로젝트 현황 업데이트"
  },
  {
    "content": "나는 시스템 프롬프트에 시나리오 인지를 추가하고 탐색 흐름을 분기하는 방향을 제안했다.",
    "type": "fact",
    "session": "2026-02-24-세션12",
    "context_hint": "시스템 프롬프트 개선 방향 제안"
  },
  {
    "content": "강재영이 '새로운 UI/UX란 AI가 동료로서 얼마나 해당 분야를 잘 이해하고 그럴듯하게 대응하느냐'라고 정의했다.",
    "type": "fact",
    "session": "2026-02-24-세션12",
    "context_hint": "UI/UX의 본질 재정의 — 강재영의 핵심 인사이트"
  },
  {
    "content": "기존에 '새 UI/UX'를 생각하면 Board, Graph, Library 같은 시각적 컴포넌트를 떠올렸다. 하지만 진짜 UI/UX는 대화의 품질이 결정한다.",
    "type": "fact",
    "session": "2026-02-24-세션12",
    "context_hint": "발현된 해석이 새로운 사실로 축적된 것 — UI/UX = 대화의 품질"
  },
  {
    "content": "도구는 키워드 검색 실행 후 결과를 나열하지만, 동료는 시나리오를 파악하고 그에 맞는 전략으로 탐색한다. 이 차이가 UI/UX의 본질이다.",
    "type": "fact",
    "session": "2026-02-24-세션12",
    "context_hint": "도구 vs 동료의 차이를 UI/UX로 연결"
  },
  {
    "content": "강재영이 모든 시나리오에 1차적 대응은 되어야 하고, 그다음 1, 2번을 고도화하겠다고 했다.",
    "type": "fact",
    "session": "2026-02-24-세션12",
    "context_hint": "구현 우선순위 확정"
  },
  {
    "content": "시스템 프롬프트에 들어갈 시나리오 인지 섹션을 설계했다. 모든 시나리오의 1차 대응(식별 + 공통 행동)과 시나리오 1, 2의 심화 전략을 포함한다.",
    "type": "fact",
    "session": "2026-02-24-세션12",
    "context_hint": "시나리오 프롬프트 섹션 설계 완료"
  },
  {
    "content": "mirror-mind 세션의 역할은 설계·조율·의사결정이고, 실제 코드 반영은 lighthouse 에이전트에게 위임하는 것이 맞다고 판단했다.",
    "type": "fact",
    "session": "2026-02-24-세션12",
    "context_hint": "mirror-mind와 lighthouse의 역할 경계 확인"
  },
  {
    "content": "나는 논의가 충분하지 않은 상태에서 설계 문서로 성급하게 넘어가는 경향이 있었다.",
    "type": "fact",
    "session": "2026-02-24-세션12",
    "context_hint": "강재영의 피드백에서 드러난 자기 인식"
  },
  {
    "content": "설계보다 연구자 행동 이해가 먼저라는 순서가 이 세션에서 확립됐다.",
    "type": "fact",
    "session": "2026-02-24-세션12",
    "context_hint": "발현된 해석이 새로운 사실로 축적된 것 — 이해 → 설계 순서"
  },
  {
    "content": "세션 종료 시 raw 파일 저장을 빠뜨렸다.",
    "type": "fact",
    "session": "2026-02-24-세션12",
    "context_hint": "종료 절차 누락"
  }
]
